numcodecs_wasm_bit_round/__init__.py
numcodecs_wasm_bit_round/__init__.pyi
numcodecs_wasm_bit_round/codec.wasm
numcodecs_wasm_bit_round/py.typed
numcodecs_wasm_bit_round-0.4.0.dist-info/METADATA
numcodecs_wasm_bit_round-0.4.0.dist-info/WHEEL
numcodecs_wasm_bit_round-0.4.0.dist-info/entry_points.txt
numcodecs_wasm_bit_round-0.4.0.dist-info/top_level.txt
numcodecs_wasm_bit_round-0.4.0.dist-info/RECORD
